Topsis_102003658/__init__.py
Topsis_102003658/topsis.py
Topsis_102003658-0.1.dist-info/METADATA
Topsis_102003658-0.1.dist-info/WHEEL
Topsis_102003658-0.1.dist-info/top_level.txt
Topsis_102003658-0.1.dist-info/RECORD
